{
  "seo_category_infos": [
    ["Beauty", "beauty"],
    ["Dance & Performance", "dance_and_performance"],
    ["Fitness", "fitness"],
    ["Food & Drink", "food_and_drink"],
    ["Home & Garden", "home_and_garden"],
    ["Music", "music"],
    ["Visual Arts", "visual_arts"]
  ],
  "logging_page_id": "profilePage_11319289292",
  "show_suggested_profiles": false,
  "show_follow_dialog": false,
  "graphql": {
    "user": {
      "biography": "I love to paint by camera \n#Photography, #Travelling, and #shoot by Camera\nDM for collaboration\n#camismyeye",
      "blocked_by_viewer": false,
      "restricted_by_viewer": null,
      "country_block": false,
      "external_url": null,
      "external_url_linkshimmed": null,
      "edge_followed_by": {
        "count": 67
      },
      "fbid": "17841411318764911",
      "followed_by_viewer": false,
      "edge_follow": {
        "count": 84
      },
      "follows_viewer": false,
      "full_name": "Click Imagine",
      "has_ar_effects": false,
      "has_clips": true,
      "has_guides": false,
      "has_channel": false,
      "has_blocked_viewer": false,
      "highlight_reel_count": 3,
      "has_requested_viewer": false,
      "hide_like_and_view_counts": false,
      "id": "11319289292",
      "is_business_account": false,
      "is_professional_account": false,
      "is_embeds_disabled": false,
      "is_joined_recently": false,
      "business_address_json": null,
      "business_contact_method": "UNKNOWN",
      "business_email": null,
      "business_phone_number": null,
      "business_category_name": null,
      "overall_category_name": null,
      "category_enum": null,
      "category_name": null,
      "is_private": false,
      "is_verified": false,
      "edge_mutual_followed_by": {
        "count": 0,
        "edges": []
      },
      "profile_pic_url": "https://instagram.fdel52-1.fna.fbcdn.net/v/t51.2885-19/s150x150/51477414_268886340669185_4693187846117261312_n.jpg?_nc_ht=instagram.fdel52-1.fna.fbcdn.net&_nc_cat=105&_nc_ohc=HZeJKD6m8CMAX_eDzSE&edm=ABfd0MgBAAAA&ccb=7-4&oh=00_AT_w6uHCD0x8K8r0mNKbsyf5oHxWLdNUxcoQZyL4Kz25kA&oe=62065FF8&_nc_sid=7bff83",
      "profile_pic_url_hd": "https://instagram.fdel52-1.fna.fbcdn.net/v/t51.2885-19/s320x320/51477414_268886340669185_4693187846117261312_n.jpg?_nc_ht=instagram.fdel52-1.fna.fbcdn.net&_nc_cat=105&_nc_ohc=HZeJKD6m8CMAX_eDzSE&edm=ABfd0MgBAAAA&ccb=7-4&oh=00_AT-IEEdZobGOu2kasWe80_Y3TmhmYa17TZst-aBHsROfnw&oe=620739C8&_nc_sid=7bff83",
      "requested_by_viewer": false,
      "should_show_category": false,
      "should_show_public_contacts": false,
      "username": "clickimaginehr",
      "connected_fb_page": null,
      "pronouns": [],
      "edge_felix_video_timeline": {
        "count": 0,
        "page_info": {
          "has_next_page": false,
          "end_cursor": null
        },
        "edges": []
      },
      "edge_owner_to_timeline_media": {
        "count": 116,
        "page_info": {
          "has_next_page": true,
          "end_cursor": "QVFBVDVyQjZ1MjJ5WFNWWXBsSDNJOVlYMFJJNFpNYTRmSUN2TDNOdWtfM05PYU50SllZVUJ1UjNxT1ctQ28zOVg3M1NPbTdNYkltTm5nRGEzT3lHYzF0aw=="
        },
        "edges": [
          {},
          {},
          {},
          {
            "node": {
              "__typename": "GraphImage",
              "id": "2752492222877460267",
              "shortcode": "CYy0Rfnoucr",
              "dimensions": {
                "height": 1346,
                "width": 1080
              },
              "display_url": "https://instagram.fdel52-1.fna.fbcdn.net/v/t51.2885-15/e35/p1080x1080/271929594_1753410438194444_1369469243014825863_n.jpg?_nc_ht=instagram.fdel52-1.fna.fbcdn.net&_nc_cat=108&_nc_ohc=bi3fhzkgF4IAX9dfxgq&edm=ABfd0MgBAAAA&ccb=7-4&oh=00_AT_8xIAQ14BmTgxry2pbsiXcvBbt-yiebFvGH-wlpQ6GIg&oe=6206413D&_nc_sid=7bff83",
              "edge_media_to_tagged_user": {
                "edges": [
                  {
                    "node": {
                      "user": {
                        "full_name": "Capture a Trip India Pvt Ltd",
                        "followed_by_viewer": false,
                        "id": "4019536061",
                        "is_verified": false,
                        "profile_pic_url": "https://instagram.fdel52-1.fna.fbcdn.net/v/t51.2885-19/s150x150/271486494_289047446620609_8934816107797596313_n.jpg?_nc_ht=instagram.fdel52-1.fna.fbcdn.net&_nc_cat=1&_nc_ohc=L5GOxn0nVD8AX8oH8iI&edm=ABfd0MgBAAAA&ccb=7-4&oh=00_AT9yuMEMpL6Brvq-BZ5ZNjEQ44yr2f6nRDmhXtYsmF6_UA&oe=620674C7&_nc_sid=7bff83",
                        "username": "capture.a.trip"
                      },
                      "x": 0.5448888889,
                      "y": 0.9836601298
                    }
                  },
                  {
                    "node": {
                      "user": {
                        "full_name": "Himalayas",
                        "followed_by_viewer": false,
                        "id": "30975058020",
                        "is_verified": false,
                        "profile_pic_url": "https://instagram.fdel52-1.fna.fbcdn.net/v/t51.2885-19/s150x150/271907911_1135259590547212_2206988664146439948_n.jpg?_nc_ht=instagram.fdel52-1.fna.fbcdn.net&_nc_cat=1&_nc_ohc=ilM-kI37Un4AX_x_MzC&edm=ABfd0MgBAAAA&ccb=7-4&oh=00_AT_WdNkJKXNa3bUepIWYH--4K-TUQC3JVplrtSv5fCfUOQ&oe=6205C9BB&_nc_sid=7bff83",
                        "username": "hills.ig"
                      },
                      "x": 0.8968888889,
                      "y": 0.8791111111
                    }
                  },
                  {
                    "node": {
                      "user": {
                        "full_name": "suicidepoint",
                        "followed_by_viewer": false,
                        "id": "10706555569",
                        "is_verified": false,
                        "profile_pic_url": "https://instagram.fdel52-1.fna.fbcdn.net/v/t51.2885-19/s150x150/50024633_241289570134748_2238487906148679680_n.jpg?_nc_ht=instagram.fdel52-1.fna.fbcdn.net&_nc_cat=108&_nc_ohc=cSCrTHm14Z4AX-NlbVk&edm=ABfd0MgBAAAA&ccb=7-4&oh=00_AT-HgvaTphIjUGWFVmlABCTx8ucSpULRkY_AsBY5SVYBSw&oe=6207733E&_nc_sid=7bff83",
                        "username": "suicide__point__007"
                      },
                      "x": 0.2693333333,
                      "y": 0.9836601298
                    }
                  }
                ]
              },
              "fact_check_overall_rating": null,
              "fact_check_information": null,
              "gating_info": null,
              "sharing_friction_info": {
                "should_have_sharing_friction": false,
                "bloks_app_url": null
              },
              "media_overlay_info": null,
              "media_preview": "ACIqh0y7MbeQ3Q5Kn9cf4VrtIo9zXLn5WDDgjr7EVooWXncefetIamc/d+ZqLIre1PZlHB5NZizYPzfmKsFyBgd+/tWliEy98vrRWZ5p9aKXKHMjIABO0j0q5nJ4qMsEwRil8xVPJ25/X8axjLlNJxcra6EhBHWnK5HHakXHT3qQJkdMV0KV1c5+RpjML70U/bRVXJ5WZoOB7HP+c9KbIRjA5B6YqaX7p+o/rVUD+dcR3mhav8uTx2qy7DpVW3HA/Gpj1P8Aumto7GMnqyXyx7/nRVLJorQx5l2P/9k=",
              "owner": {
                "id": "11319289292",
                "username": "clickimaginehr"
              },
              "is_video": false,
              "has_upcoming_event": false,
              "accessibility_caption": "Photo by Click Imagine in Sucide Point Roghi Kalpa, Kinnaur with @capture.a.trip, @suicide__point__007, and @hills.ig. May be an image of mountain and nature.",
              "edge_media_to_caption": {
                "edges": [
                  {
                    "node": {
                      "text": "#repost\nKalpa, Suicide point in himachal.\n\n(shot on the phone)\n.\nPC : @hidaytrahman\n.\n.\n.\n.\n\n#camismyeye #clickwithhidy #hills #nature #mountains #travel #uttarakhand #landscape #naturephotography #india #travelphotography #winter #hiking #clouds #himachal #sky #sunset #adventure #landscapephotography #wanderlust #love #mountain #photooftheday #instagood #himalayas #suicidepoint #forest #travelgram #trees"
                    }
                  }
                ]
              },
              "edge_media_to_comment": {
                "count": 12
              },
              "comments_disabled": false,
              "taken_at_timestamp": 1642342664,
              "edge_liked_by": {
                "count": 21
              },
              "edge_media_preview_like": {
                "count": 21
              },
              "location": {
                "id": "653219944",
                "has_public_page": true,
                "name": "Sucide Point Roghi Kalpa, Kinnaur",
                "slug": "sucide-point-roghi-kalpa-kinnaur"
              },
              "thumbnail_src": "https://instagram.fdel52-1.fna.fbcdn.net/v/t51.2885-15/sh0.08/e35/c0.177.1440.1440a/s640x640/271929594_1753410438194444_1369469243014825863_n.jpg?_nc_ht=instagram.fdel52-1.fna.fbcdn.net&_nc_cat=108&_nc_ohc=bi3fhzkgF4IAX9dfxgq&edm=ABfd0MgBAAAA&ccb=7-4&oh=00_AT8DtRefj0dGost0hfUOotKBY56R2P6aRqQx9tdgOtZmNg&oe=62061908&_nc_sid=7bff83",
              "thumbnail_resources": [
                {
                  "src": "https://instagram.fdel52-1.fna.fbcdn.net/v/t51.2885-15/e35/c0.177.1440.1440a/s150x150/271929594_1753410438194444_1369469243014825863_n.jpg?_nc_ht=instagram.fdel52-1.fna.fbcdn.net&_nc_cat=108&_nc_ohc=bi3fhzkgF4IAX9dfxgq&edm=ABfd0MgBAAAA&ccb=7-4&oh=00_AT9TLrelXT84VgBtcCe-fvnvqMQwQB33bEvf11mIT-tc_Q&oe=62077BA9&_nc_sid=7bff83",
                  "config_width": 150,
                  "config_height": 150
                },
                {
                  "src": "https://instagram.fdel52-1.fna.fbcdn.net/v/t51.2885-15/e35/c0.177.1440.1440a/s240x240/271929594_1753410438194444_1369469243014825863_n.jpg?_nc_ht=instagram.fdel52-1.fna.fbcdn.net&_nc_cat=108&_nc_ohc=bi3fhzkgF4IAX9dfxgq&edm=ABfd0MgBAAAA&ccb=7-4&oh=00_AT-HOb0kvfX_DrNc1pF3UKNSSRDhRaEH5-T-1I73IE290w&oe=6205A421&_nc_sid=7bff83",
                  "config_width": 240,
                  "config_height": 240
                },
                {
                  "src": "https://instagram.fdel52-1.fna.fbcdn.net/v/t51.2885-15/e35/c0.177.1440.1440a/s320x320/271929594_1753410438194444_1369469243014825863_n.jpg?_nc_ht=instagram.fdel52-1.fna.fbcdn.net&_nc_cat=108&_nc_ohc=bi3fhzkgF4IAX9dfxgq&edm=ABfd0MgBAAAA&ccb=7-4&oh=00_AT_6TlIdbO2SMniuwIo0rxDm40Ckn_HECznfNigRNxtBoQ&oe=62062BC0&_nc_sid=7bff83",
                  "config_width": 320,
                  "config_height": 320
                },
                {
                  "src": "https://instagram.fdel52-1.fna.fbcdn.net/v/t51.2885-15/e35/c0.177.1440.1440a/s480x480/271929594_1753410438194444_1369469243014825863_n.jpg?_nc_ht=instagram.fdel52-1.fna.fbcdn.net&_nc_cat=108&_nc_ohc=bi3fhzkgF4IAX9dfxgq&edm=ABfd0MgBAAAA&ccb=7-4&oh=00_AT_BRJ9ackkeF3J6yZC8pXMRpOVDO7dvdTYTRQ5Fqs59Ng&oe=6206E87E&_nc_sid=7bff83",
                  "config_width": 480,
                  "config_height": 480
                },
                {
                  "src": "https://instagram.fdel52-1.fna.fbcdn.net/v/t51.2885-15/sh0.08/e35/c0.177.1440.1440a/s640x640/271929594_1753410438194444_1369469243014825863_n.jpg?_nc_ht=instagram.fdel52-1.fna.fbcdn.net&_nc_cat=108&_nc_ohc=bi3fhzkgF4IAX9dfxgq&edm=ABfd0MgBAAAA&ccb=7-4&oh=00_AT8DtRefj0dGost0hfUOotKBY56R2P6aRqQx9tdgOtZmNg&oe=62061908&_nc_sid=7bff83",
                  "config_width": 640,
                  "config_height": 640
                }
              ],
              "coauthor_producers": []
            }
          },
          {
            "node": {
              "__typename": "GraphVideo",
              "id": "2750780294454168887",
              "shortcode": "CYsvBqCFc03",
              "dimensions": {
                "height": 1920,
                "width": 1080
              },
              "display_url": "https://instagram.fdel52-1.fna.fbcdn.net/v/t51.2885-15/fr/e15/p1080x1080/271705606_2144327502403243_799464477510285334_n.jpg?_nc_ht=instagram.fdel52-1.fna.fbcdn.net&_nc_cat=107&_nc_ohc=SiviHA7tK4gAX8E7USR&edm=ABfd0MgBAAAA&ccb=7-4&oh=00_AT9_FqtmhyENk2Ra-dqjFS0_Elgq-gadPq_EGN02Qv3i0g&oe=6201B03A&_nc_sid=7bff83",
              "edge_media_to_tagged_user": {
                "edges": []
              },
              "fact_check_overall_rating": null,
              "fact_check_information": null,
              "gating_info": null,
              "sharing_friction_info": {
                "should_have_sharing_friction": false,
                "bloks_app_url": null
              },
              "media_overlay_info": null,
              "media_preview": "ABgqkIphFWmSoytd6ZwNFciipCtFMkBfL/EM+4q2hWUZU5rmg2aesxQ8HBrM2szoTHRWRDqDLxwfrRRqJruZ7e1IU5yelSL0qOpNbiABaKbRQOx//9k=",
              "owner": {
                "id": "11319289292",
                "username": "clickimaginehr"
              },
              "is_video": true,
              "has_upcoming_event": false,
              "accessibility_caption": null,
              "dash_info": {
                "is_dash_eligible": false,
                "video_dash_manifest": null,
                "number_of_qualities": 0
              },
              "has_audio": true,
              "tracking_token": "eyJ2ZXJzaW9uIjo1LCJwYXlsb2FkIjp7ImlzX2FuYWx5dGljc190cmFja2VkIjpmYWxzZSwidXVpZCI6ImUwMmFlY2MwMzAxZTQ4ZDk4ZTdmOWE2NTQ3Zjg3NWEyMjc1MDc4MDI5NDQ1NDE2ODg4NyJ9LCJzaWduYXR1cmUiOiIifQ==",
              "video_url": "https://instagram.fdel52-1.fna.fbcdn.net/v/t50.2886-16/271553665_925234928352637_327242085427775842_n.mp4?_nc_ht=instagram.fdel52-1.fna.fbcdn.net&_nc_cat=101&_nc_ohc=VPDJtGRTyCkAX-JenH3&edm=ABfd0MgBAAAA&ccb=7-4&oe=6201CFCA&oh=00_AT_7k8d6RLF-SysULBL2MK8m3MtDlm2gFsZxT28Wbk3jjg&_nc_sid=7bff83",
              "video_view_count": 874,
              "edge_media_to_caption": {
                "edges": [
                  {
                    "node": {
                      "text": "Khoobsoorat rastey.\n\n.\n.\n.\n#himachal #clickwithhidy #journey #travel #roadtrips #india"
                    }
                  }
                ]
              },
              "edge_media_to_comment": {
                "count": 2
              },
              "comments_disabled": false,
              "taken_at_timestamp": 1642138661,
              "edge_liked_by": {
                "count": 110
              },
              "edge_media_preview_like": {
                "count": 110
              },
              "location": null,
              "thumbnail_src": "https://instagram.fdel52-1.fna.fbcdn.net/v/t51.2885-15/sh0.08/e35/c0.420.1080.1080a/s640x640/271705606_2144327502403243_799464477510285334_n.jpg?_nc_ht=instagram.fdel52-1.fna.fbcdn.net&_nc_cat=107&_nc_ohc=SiviHA7tK4gAX8E7USR&edm=ABfd0MgBAAAA&ccb=7-4&oh=00_AT8G4kcQSGs85lIVRDdf3p3rUGjHm0Cq01_hQ30Ei6Ru0g&oe=62021CC9&_nc_sid=7bff83",
              "thumbnail_resources": [
                {
                  "src": "https://instagram.fdel52-1.fna.fbcdn.net/v/t51.2885-15/e15/c0.420.1080.1080a/s150x150/271705606_2144327502403243_799464477510285334_n.jpg?_nc_ht=instagram.fdel52-1.fna.fbcdn.net&_nc_cat=107&_nc_ohc=SiviHA7tK4gAX8E7USR&edm=ABfd0MgBAAAA&ccb=7-4&oh=00_AT__mqjTpASqK6lhAw1ys_pJzNPP6jRj_lKSA4cxbh7S5g&oe=6202031F&_nc_sid=7bff83",
                  "config_width": 150,
                  "config_height": 150
                },
                {
                  "src": "https://instagram.fdel52-1.fna.fbcdn.net/v/t51.2885-15/e15/c0.420.1080.1080a/s240x240/271705606_2144327502403243_799464477510285334_n.jpg?_nc_ht=instagram.fdel52-1.fna.fbcdn.net&_nc_cat=107&_nc_ohc=SiviHA7tK4gAX8E7USR&edm=ABfd0MgBAAAA&ccb=7-4&oh=00_AT8PopqNiVeBUL1gZ0exOd53iyRZyvJaCAPXHzqOE-zI5Q&oe=6201DCD9&_nc_sid=7bff83",
                  "config_width": 240,
                  "config_height": 240
                },
                {
                  "src": "https://instagram.fdel52-1.fna.fbcdn.net/v/t51.2885-15/e15/c0.420.1080.1080a/s320x320/271705606_2144327502403243_799464477510285334_n.jpg?_nc_ht=instagram.fdel52-1.fna.fbcdn.net&_nc_cat=107&_nc_ohc=SiviHA7tK4gAX8E7USR&edm=ABfd0MgBAAAA&ccb=7-4&oh=00_AT-5SwTqklQd9miXqKv_YU_XB5HTPputqtywwBch0gjugw&oe=6201CD67&_nc_sid=7bff83",
                  "config_width": 320,
                  "config_height": 320
                },
                {
                  "src": "https://instagram.fdel52-1.fna.fbcdn.net/v/t51.2885-15/e15/c0.420.1080.1080a/s480x480/271705606_2144327502403243_799464477510285334_n.jpg?_nc_ht=instagram.fdel52-1.fna.fbcdn.net&_nc_cat=107&_nc_ohc=SiviHA7tK4gAX8E7USR&edm=ABfd0MgBAAAA&ccb=7-4&oh=00_AT84PizqseWCT0aKn89QwuZU0cbo9flt9-Y8zlxQ5AnvnQ&oe=6201EA22&_nc_sid=7bff83",
                  "config_width": 480,
                  "config_height": 480
                },
                {
                  "src": "https://instagram.fdel52-1.fna.fbcdn.net/v/t51.2885-15/sh0.08/e35/c0.420.1080.1080a/s640x640/271705606_2144327502403243_799464477510285334_n.jpg?_nc_ht=instagram.fdel52-1.fna.fbcdn.net&_nc_cat=107&_nc_ohc=SiviHA7tK4gAX8E7USR&edm=ABfd0MgBAAAA&ccb=7-4&oh=00_AT8G4kcQSGs85lIVRDdf3p3rUGjHm0Cq01_hQ30Ei6Ru0g&oe=62021CC9&_nc_sid=7bff83",
                  "config_width": 640,
                  "config_height": 640
                }
              ],
              "felix_profile_grid_crop": null,
              "coauthor_producers": [],
              "product_type": "clips",
              "clips_music_attribution_info": null
            }
          },
          {
            "node": {
              "__typename": "GraphImage",
              "id": "2734466627195207365",
              "shortcode": "CXyxujcIX7F",
              "dimensions": {
                "height": 1350,
                "width": 1080
              },
              "display_url": "https://instagram.fdel52-1.fna.fbcdn.net/v/t51.2885-15/e35/p1080x1080/269897557_1271673396665381_6165961882245731084_n.jpg?_nc_ht=instagram.fdel52-1.fna.fbcdn.net&_nc_cat=105&_nc_ohc=cgl8JiDu2LMAX9qLc5G&edm=ABfd0MgBAAAA&ccb=7-4&oh=00_AT8-4jrpauNW3yCmAZcuPJvnFpN-cS1fzzT9fCdTcpDEtQ&oe=6206E3CC&_nc_sid=7bff83",
              "edge_media_to_tagged_user": {
                "edges": [
                  {
                    "node": {
                      "user": {
                        "full_name": "Hidayt Rahman",
                        "followed_by_viewer": false,
                        "id": "3280824343",
                        "is_verified": false,
                        "profile_pic_url": "https://instagram.fdel52-1.fna.fbcdn.net/v/t51.2885-19/s150x150/271896126_650254582841380_43292338451860659_n.jpg?_nc_ht=instagram.fdel52-1.fna.fbcdn.net&_nc_cat=104&_nc_ohc=TEXlledQFZsAX96KEdD&edm=ABfd0MgBAAAA&ccb=7-4&oh=00_AT_Nff30aHli9zOTqmGyXNBkhj0qkJjqHSUMrbKqZl7IMA&oe=62076EE4&_nc_sid=7bff83",
                        "username": "hidaytrahman"
                      },
                      "x": 0.5,
                      "y": 0.5
                    }
                  }
                ]
              },
              "fact_check_overall_rating": null,
              "fact_check_information": null,
              "gating_info": null,
              "sharing_friction_info": {
                "should_have_sharing_friction": false,
                "bloks_app_url": null
              },
              "media_overlay_info": null,
              "media_preview": "ACIqogVIBTBUoruOEeoqZaiFSrSGSUUtFAyUwQk4x+vSntbQJyfl46ZrKS7AJ83DZ/TPHb2qd0iUgjLHr1Ppxz6f/qrC7va7NrLeyLxjiPGMcduKUwwnoSOx7/zqis7txnjjGO3tUNxN5bDaeoyQODz3Gev5U7tdQ0fQ1fs8f9/9KKwftQ/vN+Q/+KoqeZ9/yHyrt+ZUYg8/Tj8frVyGQhcE5XsD2+n+cGqB4bj1qyPu0o7jlsXN/ljJ4FU5J0mPIHy9COpHbOcjj+tMlP7o/hVEk05MIo0DATyNvP1/xoqlvb1P50UtA17n/9k=",
              "owner": {
                "id": "11319289292",
                "username": "clickimaginehr"
              },
              "is_video": false,
              "has_upcoming_event": false,
              "accessibility_caption": "Photo by Click Imagine in Kalpa, Himachal Pradesh with @hidaytrahman. May be an image of nature, tree and mountain.",
              "edge_media_to_caption": {
                "edges": [
                  {
                    "node": {
                      "text": "Kalpa is a small village in the Sutlej river valley, above Reckong Peo in the Kinnaur district of Himachal Pradesh, Northern India, in the Indian Himalaya. Inhabited by Kinnauri people and known for its apple orchards. Apples are a major cash-crop for the region.\n\n(shot on the phone)\n.\nPC : @hidaytrahman\n.\n.\n.\n.\n\n#camismyeye #clickwithhidy #hills #nature #mountains #travel #uttarakhand #landscape #naturephotography #india #travelphotography #winter #hiking #clouds #himachal #sky #sunset #adventure #landscapephotography #wanderlust #love #mountain #snow #photooftheday #instagood #himalayas #sissuhimachal #forest #travelgram #trees"
                    }
                  }
                ]
              },
              "edge_media_to_comment": {
                "count": 6
              },
              "comments_disabled": false,
              "taken_at_timestamp": 1640193845,
              "edge_liked_by": {
                "count": 24
              },
              "edge_media_preview_like": {
                "count": 24
              },
              "location": {
                "id": "281902510",
                "has_public_page": true,
                "name": "Kalpa, Himachal Pradesh",
                "slug": "kalpa-himachal-pradesh"
              },
              "thumbnail_src": "https://instagram.fdel52-1.fna.fbcdn.net/v/t51.2885-15/sh0.08/e35/c0.180.1440.1440a/s640x640/269897557_1271673396665381_6165961882245731084_n.jpg?_nc_ht=instagram.fdel52-1.fna.fbcdn.net&_nc_cat=105&_nc_ohc=cgl8JiDu2LMAX9qLc5G&edm=ABfd0MgBAAAA&ccb=7-4&oh=00_AT84fNzdeQlqPq2c9G-LKvwMjjd-DeXGAc1oeVFyE3WDBA&oe=6206D6CF&_nc_sid=7bff83",
              "thumbnail_resources": [
                {
                  "src": "https://instagram.fdel52-1.fna.fbcdn.net/v/t51.2885-15/e35/c0.180.1440.1440a/s150x150/269897557_1271673396665381_6165961882245731084_n.jpg?_nc_ht=instagram.fdel52-1.fna.fbcdn.net&_nc_cat=105&_nc_ohc=cgl8JiDu2LMAX9qLc5G&edm=ABfd0MgBAAAA&ccb=7-4&oh=00_AT9tlZFYKuaDw6gOuAk3LLtfbSq_8w8dKXZhyGmSAsHEgg&oe=620641E2&_nc_sid=7bff83",
                  "config_width": 150,
                  "config_height": 150
                },
                {
                  "src": "https://instagram.fdel52-1.fna.fbcdn.net/v/t51.2885-15/e35/c0.180.1440.1440a/s240x240/269897557_1271673396665381_6165961882245731084_n.jpg?_nc_ht=instagram.fdel52-1.fna.fbcdn.net&_nc_cat=105&_nc_ohc=cgl8JiDu2LMAX9qLc5G&edm=ABfd0MgBAAAA&ccb=7-4&oh=00_AT8NqbDuis9ib-wMcilE4KkzHuWEt6OLTOO-4ejCpWgK-Q&oe=6205C02A&_nc_sid=7bff83",
                  "config_width": 240,
                  "config_height": 240
                },
                {
                  "src": "https://instagram.fdel52-1.fna.fbcdn.net/v/t51.2885-15/e35/c0.180.1440.1440a/s320x320/269897557_1271673396665381_6165961882245731084_n.jpg?_nc_ht=instagram.fdel52-1.fna.fbcdn.net&_nc_cat=105&_nc_ohc=cgl8JiDu2LMAX9qLc5G&edm=ABfd0MgBAAAA&ccb=7-4&oh=00_AT-dGuK4D4pe4I0mm3TDfw77uSddK9kPYtPPAu7E_iiYTg&oe=62067137&_nc_sid=7bff83",
                  "config_width": 320,
                  "config_height": 320
                },
                {
                  "src": "https://instagram.fdel52-1.fna.fbcdn.net/v/t51.2885-15/e35/c0.180.1440.1440a/s480x480/269897557_1271673396665381_6165961882245731084_n.jpg?_nc_ht=instagram.fdel52-1.fna.fbcdn.net&_nc_cat=105&_nc_ohc=cgl8JiDu2LMAX9qLc5G&edm=ABfd0MgBAAAA&ccb=7-4&oh=00_AT9TrNRx-BcrEF0nlyhu-9_mo4GsoA_IftJe13hpmmNkYQ&oe=6206BA35&_nc_sid=7bff83",
                  "config_width": 480,
                  "config_height": 480
                },
                {
                  "src": "https://instagram.fdel52-1.fna.fbcdn.net/v/t51.2885-15/sh0.08/e35/c0.180.1440.1440a/s640x640/269897557_1271673396665381_6165961882245731084_n.jpg?_nc_ht=instagram.fdel52-1.fna.fbcdn.net&_nc_cat=105&_nc_ohc=cgl8JiDu2LMAX9qLc5G&edm=ABfd0MgBAAAA&ccb=7-4&oh=00_AT84fNzdeQlqPq2c9G-LKvwMjjd-DeXGAc1oeVFyE3WDBA&oe=6206D6CF&_nc_sid=7bff83",
                  "config_width": 640,
                  "config_height": 640
                }
              ],
              "coauthor_producers": []
            }
          },
          {
            "node": {
              "__typename": "GraphImage",
              "id": "2707628028829045443",
              "shortcode": "CWTbVi6PxLD",
              "dimensions": {
                "height": 878,
                "width": 1080
              },
              "display_url": "https://instagram.fdel52-1.fna.fbcdn.net/v/t51.2885-15/e35/s1080x1080/256480946_1298620180585710_1863234555517259690_n.jpg?_nc_ht=instagram.fdel52-1.fna.fbcdn.net&_nc_cat=106&_nc_ohc=TitZ5a918EoAX_Ck162&edm=ABfd0MgBAAAA&ccb=7-4&oh=00_AT-endqKMlFt4JW6-tMhdGBRvEgwtVk-haJSMdry5MV4gg&oe=62070BF6&_nc_sid=7bff83",
              "edge_media_to_tagged_user": {
                "edges": [
                  {
                    "node": {
                      "user": {
                        "full_name": "Capture a Trip India Pvt Ltd",
                        "followed_by_viewer": false,
                        "id": "4019536061",
                        "is_verified": false,
                        "profile_pic_url": "https://instagram.fdel52-1.fna.fbcdn.net/v/t51.2885-19/s150x150/271486494_289047446620609_8934816107797596313_n.jpg?_nc_ht=instagram.fdel52-1.fna.fbcdn.net&_nc_cat=1&_nc_ohc=L5GOxn0nVD8AX8oH8iI&edm=ABfd0MgBAAAA&ccb=7-4&oh=00_AT9yuMEMpL6Brvq-BZ5ZNjEQ44yr2f6nRDmhXtYsmF6_UA&oe=620674C7&_nc_sid=7bff83",
                        "username": "capture.a.trip"
                      },
                      "x": 0.5,
                      "y": 0.5
                    }
                  },
                  {
                    "node": {
                      "user": {
                        "full_name": "Hidayt Rahman",
                        "followed_by_viewer": false,
                        "id": "3280824343",
                        "is_verified": false,
                        "profile_pic_url": "https://instagram.fdel52-1.fna.fbcdn.net/v/t51.2885-19/s150x150/271896126_650254582841380_43292338451860659_n.jpg?_nc_ht=instagram.fdel52-1.fna.fbcdn.net&_nc_cat=104&_nc_ohc=TEXlledQFZsAX96KEdD&edm=ABfd0MgBAAAA&ccb=7-4&oh=00_AT_Nff30aHli9zOTqmGyXNBkhj0qkJjqHSUMrbKqZl7IMA&oe=62076EE4&_nc_sid=7bff83",
                        "username": "hidaytrahman"
                      },
                      "x": 0.091555542,
                      "y": 0.9836601298
                    }
                  }
                ]
              },
              "fact_check_overall_rating": null,
              "fact_check_information": null,
              "gating_info": null,
              "sharing_friction_info": {
                "should_have_sharing_friction": false,
                "bloks_app_url": null
              },
              "media_overlay_info": null,
              "media_preview": "ACoi02G0/Mob0Kj/ACaqTlQQUyjehz/Wq4kI7kYoM5YYPzfWqJCaRkO0EHuT1znv7VFHLIvuPfpT9zdQAKkEzKMEbQe3Y/pRdDsNdzJycdKi2iriMjDg8+h603bH6j9aq4inu7mmiUZyDn1qRDESSeAemc/p/nFMZIhwGOemP8iudtlDTKCPQ4z3/KkWZWHzHdwDzxSRqjE7yRzwccfj70SLEnQ7geDwelT94yUFW4BxipPL9z+VVd0YO/2/Tp09RTsL23VOvmBCOX/CpG60UVTAilPyn6mmp0/P+VFFC2AegyFzzxVqiiokB//Z",
              "owner": {
                "id": "11319289292",
                "username": "clickimaginehr"
              },
              "is_video": false,
              "has_upcoming_event": false,
              "accessibility_caption": "Photo by Click Imagine in Himachal Pradesh with @hidaytrahman, and @capture.a.trip. May be an image of tree, sky, nature and mountain.",
              "edge_media_to_caption": {
                "edges": [
                  {
                    "node": {
                      "text": "Somewhere, on the way to sissu.\n\n(shot on the phone)\n.\nPC : @hidaytrahman\n.\n.\n.\n.\n\n#camismyeye #clickwithhidy #hills #nature #mountains #travel #uttarakhand #landscape #naturephotography #india #travelphotography #winter #hiking #clouds #himachal #sky #sunset #adventure #landscapephotography #wanderlust #love #mountain #snow #photooftheday #instagood #himalayas #sissuhimachal #forest #travelgram #trees"
                    }
                  }
                ]
              },
              "edge_media_to_comment": {
                "count": 1
              },
              "comments_disabled": false,
              "taken_at_timestamp": 1636994435,
              "edge_liked_by": {
                "count": 20
              },
              "edge_media_preview_like": {
                "count": 20
              },
              "location": {
                "id": "252633351",
                "has_public_page": true,
                "name": "Himachal Pradesh",
                "slug": "himachal-pradesh"
              },
              "thumbnail_src": "https://instagram.fdel52-1.fna.fbcdn.net/v/t51.2885-15/sh0.08/e35/c134.0.1171.1171a/s640x640/256480946_1298620180585710_1863234555517259690_n.jpg?_nc_ht=instagram.fdel52-1.fna.fbcdn.net&_nc_cat=106&_nc_ohc=TitZ5a918EoAX_Ck162&edm=ABfd0MgBAAAA&ccb=7-4&oh=00_AT_oMt3HDhcStOSOeO5UVJipztAbqH0z7h9PoV3uRRD_sA&oe=6206837A&_nc_sid=7bff83",
              "thumbnail_resources": [
                {
                  "src": "https://instagram.fdel52-1.fna.fbcdn.net/v/t51.2885-15/e35/c134.0.1171.1171a/s150x150/256480946_1298620180585710_1863234555517259690_n.jpg?_nc_ht=instagram.fdel52-1.fna.fbcdn.net&_nc_cat=106&_nc_ohc=TitZ5a918EoAX_Ck162&edm=ABfd0MgBAAAA&ccb=7-4&oh=00_AT_dOIHL44WKM1gzejVzvCKIUBRjGgnEvyc6XI4gRn6TQA&oe=62074517&_nc_sid=7bff83",
                  "config_width": 150,
                  "config_height": 150
                },
                {
                  "src": "https://instagram.fdel52-1.fna.fbcdn.net/v/t51.2885-15/e35/c134.0.1171.1171a/s240x240/256480946_1298620180585710_1863234555517259690_n.jpg?_nc_ht=instagram.fdel52-1.fna.fbcdn.net&_nc_cat=106&_nc_ohc=TitZ5a918EoAX_Ck162&edm=ABfd0MgBAAAA&ccb=7-4&oh=00_AT_4G6k8pEK6SX-VeSKUVLq6NdAiTQRvdFxtCM_M_ogEBA&oe=62078EDF&_nc_sid=7bff83",
                  "config_width": 240,
                  "config_height": 240
                },
                {
                  "src": "https://instagram.fdel52-1.fna.fbcdn.net/v/t51.2885-15/e35/c134.0.1171.1171a/s320x320/256480946_1298620180585710_1863234555517259690_n.jpg?_nc_ht=instagram.fdel52-1.fna.fbcdn.net&_nc_cat=106&_nc_ohc=TitZ5a918EoAX_Ck162&edm=ABfd0MgBAAAA&ccb=7-4&oh=00_AT9Tqbiv-30Cua6SUwwdk95EvUmDgcafiT5NPM218XPwxA&oe=620664C2&_nc_sid=7bff83",
                  "config_width": 320,
                  "config_height": 320
                },
                {
                  "src": "https://instagram.fdel52-1.fna.fbcdn.net/v/t51.2885-15/e35/c134.0.1171.1171a/s480x480/256480946_1298620180585710_1863234555517259690_n.jpg?_nc_ht=instagram.fdel52-1.fna.fbcdn.net&_nc_cat=106&_nc_ohc=TitZ5a918EoAX_Ck162&edm=ABfd0MgBAAAA&ccb=7-4&oh=00_AT9BLNOGZR7MnCMy7yTJfqcYcb2fmqcft7wnZqRI9cshTg&oe=620662C4&_nc_sid=7bff83",
                  "config_width": 480,
                  "config_height": 480
                },
                {
                  "src": "https://instagram.fdel52-1.fna.fbcdn.net/v/t51.2885-15/sh0.08/e35/c134.0.1171.1171a/s640x640/256480946_1298620180585710_1863234555517259690_n.jpg?_nc_ht=instagram.fdel52-1.fna.fbcdn.net&_nc_cat=106&_nc_ohc=TitZ5a918EoAX_Ck162&edm=ABfd0MgBAAAA&ccb=7-4&oh=00_AT_oMt3HDhcStOSOeO5UVJipztAbqH0z7h9PoV3uRRD_sA&oe=6206837A&_nc_sid=7bff83",
                  "config_width": 640,
                  "config_height": 640
                }
              ],
              "coauthor_producers": []
            }
          },
          {
            "node": {
              "__typename": "GraphImage",
              "id": "2701764671362227029",
              "shortcode": "CV-mKdvPttV",
              "dimensions": {
                "height": 1350,
                "width": 1080
              },
              "display_url": "https://instagram.fdel52-1.fna.fbcdn.net/v/t51.2885-15/e35/p1080x1080/253936293_876098519939032_4333782827323995713_n.jpg?_nc_ht=instagram.fdel52-1.fna.fbcdn.net&_nc_cat=104&_nc_ohc=BV15v2yuiEoAX9uLj4I&edm=ABfd0MgBAAAA&ccb=7-4&oh=00_AT-1XtUNP6BuW4IJw5kgMfSQvFgd_wOKPd-9YzLVWwVyhw&oe=6206A532&_nc_sid=7bff83",
              "edge_media_to_tagged_user": {
                "edges": [
                  {
                    "node": {
                      "user": {
                        "full_name": "Capture a Trip India Pvt Ltd",
                        "followed_by_viewer": false,
                        "id": "4019536061",
                        "is_verified": false,
                        "profile_pic_url": "https://instagram.fdel52-1.fna.fbcdn.net/v/t51.2885-19/s150x150/271486494_289047446620609_8934816107797596313_n.jpg?_nc_ht=instagram.fdel52-1.fna.fbcdn.net&_nc_cat=1&_nc_ohc=L5GOxn0nVD8AX8oH8iI&edm=ABfd0MgBAAAA&ccb=7-4&oh=00_AT9yuMEMpL6Brvq-BZ5ZNjEQ44yr2f6nRDmhXtYsmF6_UA&oe=620674C7&_nc_sid=7bff83",
                        "username": "capture.a.trip"
                      },
                      "x": 0.8408888889,
                      "y": 0.968
                    }
                  },
                  {
                    "node": {
                      "user": {
                        "full_name": "Hidayt Rahman",
                        "followed_by_viewer": false,
                        "id": "3280824343",
                        "is_verified": false,
                        "profile_pic_url": "https://instagram.fdel52-1.fna.fbcdn.net/v/t51.2885-19/s150x150/271896126_650254582841380_43292338451860659_n.jpg?_nc_ht=instagram.fdel52-1.fna.fbcdn.net&_nc_cat=104&_nc_ohc=TEXlledQFZsAX96KEdD&edm=ABfd0MgBAAAA&ccb=7-4&oh=00_AT_Nff30aHli9zOTqmGyXNBkhj0qkJjqHSUMrbKqZl7IMA&oe=62076EE4&_nc_sid=7bff83",
                        "username": "hidaytrahman"
                      },
                      "x": 0.1724444444,
                      "y": 0.9836601298
                    }
                  },
                  {
                    "node": {
                      "user": {
                        "full_name": "Himachali culture 😍",
                        "followed_by_viewer": false,
                        "id": "34845826482",
                        "is_verified": false,
                        "profile_pic_url": "https://instagram.fdel52-1.fna.fbcdn.net/v/t51.2885-19/s150x150/183646109_539222290581781_5201092806016540312_n.jpg?_nc_ht=instagram.fdel52-1.fna.fbcdn.net&_nc_cat=101&_nc_ohc=AHIdysq7U1UAX_fNeh9&edm=ABfd0MgBAAAA&ccb=7-4&oh=00_AT_69z9l5DDeJ9Kp_f507LzAUAJfc3LK-00J3Dpd-VczSg&oe=6206ED70&_nc_sid=7bff83",
                        "username": "himachal__culture"
                      },
                      "x": 0.1182222222,
                      "y": 0.9836601298
                    }
                  },
                  {
                    "node": {
                      "user": {
                        "full_name": "IndiaKeHills",
                        "followed_by_viewer": false,
                        "id": "32789687129",
                        "is_verified": false,
                        "profile_pic_url": "https://instagram.fdel52-1.fna.fbcdn.net/v/t51.2885-19/s150x150/95257872_522260601775878_6919245567155503104_n.jpg?_nc_ht=instagram.fdel52-1.fna.fbcdn.net&_nc_cat=106&_nc_ohc=U1PW236VOCMAX9-0mPI&edm=ABfd0MgBAAAA&ccb=7-4&oh=00_AT-4LhL7cds9V5vyniKHneNakTROpLyUNIiqslWai2_04g&oe=6207731F&_nc_sid=7bff83",
                        "username": "indiakehills"
                      },
                      "x": 0.1217777507,
                      "y": 0.795555542
                    }
                  }
                ]
              },
              "fact_check_overall_rating": null,
              "fact_check_information": null,
              "gating_info": null,
              "sharing_friction_info": {
                "should_have_sharing_friction": false,
                "bloks_app_url": null
              },
              "media_overlay_info": null,
              "media_preview": "ACIquYpGUgU9Tz0p5xWpkRhCeelKykVIVULnPNQk5oGMxRTsUUxEiLj2pJXVepGT0Hc/SmFz1Iqnuwdz4JOQBjn/AD+NIBX81jlTgfhj8/Wkkm8pcuR7AHJP6VWkgEsh6gdxnPP4en+TU6W6xjgcjvjn+g+lAykbyTsOPxoq9+J/P/7Kip17j0M3zC3BOfqf51OLpl6BaqD+tPA61lr3GT/a5P8AZ59qT7U49B+A/wAKZGAfzFN/i/H+tF33Af50h5z/AOOj/CiqZY560UXfcqx//9k=",
              "owner": {
                "id": "11319289292",
                "username": "clickimaginehr"
              },
              "is_video": false,
              "has_upcoming_event": false,
              "accessibility_caption": "Photo by Click Imagine in Sissu, Himachal Pradesh with @hidaytrahman, @capture.a.trip, @indiakehills, and @himachal__culture. May be an image of nature.",
              "edge_media_to_caption": {
                "edges": [
                  {
                    "node": {
                      "text": "Can’t get a view like this in a hotel.\n\n(shot on the phone)\n.\nPC : @hidaytrahman\n\nTrip credit : @capture.a.trip \n.\n.\n.\n.\n\n#camismyeye #clickwithhidy #hills #nature #mountains #travel #uttarakhand #landscape #naturephotography #india #travelphotography #winter #hiking #clouds #himachal #sky #sunset #adventure #landscapephotography #wanderlust #love #mountain #snow #photooftheday #instagood #himalayas #sissuhimachal #forest #travelgram #trees"
                    }
                  }
                ]
              },
              "edge_media_to_comment": {
                "count": 3
              },
              "comments_disabled": false,
              "taken_at_timestamp": 1636295468,
              "edge_liked_by": {
                "count": 20
              },
              "edge_media_preview_like": {
                "count": 20
              },
              "location": {
                "id": "111283337340018",
                "has_public_page": true,
                "name": "Sissu, Himachal Pradesh",
                "slug": "sissu-himachal-pradesh"
              },
              "thumbnail_src": "https://instagram.fdel52-1.fna.fbcdn.net/v/t51.2885-15/sh0.08/e35/c0.180.1440.1440a/s640x640/253936293_876098519939032_4333782827323995713_n.jpg?_nc_ht=instagram.fdel52-1.fna.fbcdn.net&_nc_cat=104&_nc_ohc=BV15v2yuiEoAX9uLj4I&edm=ABfd0MgBAAAA&ccb=7-4&oh=00_AT9hl4Vdl6yKuA9N25fLuFS-5yza6LHXYY2AqCaeXemXMA&oe=6205D956&_nc_sid=7bff83",
              "thumbnail_resources": [
                {
                  "src": "https://instagram.fdel52-1.fna.fbcdn.net/v/t51.2885-15/e35/c0.180.1440.1440a/s150x150/253936293_876098519939032_4333782827323995713_n.jpg?_nc_ht=instagram.fdel52-1.fna.fbcdn.net&_nc_cat=104&_nc_ohc=BV15v2yuiEoAX9uLj4I&edm=ABfd0MgBAAAA&ccb=7-4&oh=00_AT_Fv8Redg0nkJq4RuVe7IB9I_G_ayXStWg23U_XZlUI1Q&oe=6206FB26&_nc_sid=7bff83",
                  "config_width": 150,
                  "config_height": 150
                },
                {
                  "src": "https://instagram.fdel52-1.fna.fbcdn.net/v/t51.2885-15/e35/c0.180.1440.1440a/s240x240/253936293_876098519939032_4333782827323995713_n.jpg?_nc_ht=instagram.fdel52-1.fna.fbcdn.net&_nc_cat=104&_nc_ohc=BV15v2yuiEoAX9uLj4I&edm=ABfd0MgBAAAA&ccb=7-4&oh=00_AT8CeIx-sZQ5dHWdDsBukuLaIjNVekXqM7tUHbGFrwSIGA&oe=62072CA4&_nc_sid=7bff83",
                  "config_width": 240,
                  "config_height": 240
                },
                {
                  "src": "https://instagram.fdel52-1.fna.fbcdn.net/v/t51.2885-15/e35/c0.180.1440.1440a/s320x320/253936293_876098519939032_4333782827323995713_n.jpg?_nc_ht=instagram.fdel52-1.fna.fbcdn.net&_nc_cat=104&_nc_ohc=BV15v2yuiEoAX9uLj4I&edm=ABfd0MgBAAAA&ccb=7-4&oh=00_AT9E0oArdgRFgbMrRFthmhM0ZmdbFQ9BC3M-XY2P0f9G-g&oe=6205C6DE&_nc_sid=7bff83",
                  "config_width": 320,
                  "config_height": 320
                },
                {
                  "src": "https://instagram.fdel52-1.fna.fbcdn.net/v/t51.2885-15/e35/c0.180.1440.1440a/s480x480/253936293_876098519939032_4333782827323995713_n.jpg?_nc_ht=instagram.fdel52-1.fna.fbcdn.net&_nc_cat=104&_nc_ohc=BV15v2yuiEoAX9uLj4I&edm=ABfd0MgBAAAA&ccb=7-4&oh=00_AT_t-7iTT7M3nZikxhF1gLoQOMpCKV7dDyZneJMEs7yZ3Q&oe=6206FD9B&_nc_sid=7bff83",
                  "config_width": 480,
                  "config_height": 480
                },
                {
                  "src": "https://instagram.fdel52-1.fna.fbcdn.net/v/t51.2885-15/sh0.08/e35/c0.180.1440.1440a/s640x640/253936293_876098519939032_4333782827323995713_n.jpg?_nc_ht=instagram.fdel52-1.fna.fbcdn.net&_nc_cat=104&_nc_ohc=BV15v2yuiEoAX9uLj4I&edm=ABfd0MgBAAAA&ccb=7-4&oh=00_AT9hl4Vdl6yKuA9N25fLuFS-5yza6LHXYY2AqCaeXemXMA&oe=6205D956&_nc_sid=7bff83",
                  "config_width": 640,
                  "config_height": 640
                }
              ],
              "coauthor_producers": []
            }
          },
          {
            "node": {
              "__typename": "GraphImage",
              "id": "2686565712237385692",
              "shortcode": "CVImUf_p1fc",
              "dimensions": {
                "height": 810,
                "width": 1080
              },
              "display_url": "https://instagram.fdel52-1.fna.fbcdn.net/v/t51.2885-15/e35/s1080x1080/246397481_263940265648019_5831476138451305625_n.jpg?_nc_ht=instagram.fdel52-1.fna.fbcdn.net&_nc_cat=111&_nc_ohc=uXrt5kuGznEAX9OfKoJ&edm=ABfd0MgBAAAA&ccb=7-4&oh=00_AT-eEU9gDxOOkS3LzjL1Qhn_t7iW_M3Rrnyv0j0mI4ULXw&oe=620670FC&_nc_sid=7bff83",
              "edge_media_to_tagged_user": {
                "edges": []
              },
              "fact_check_overall_rating": null,
              "fact_check_information": null,
              "gating_info": null,
              "sharing_friction_info": {
                "should_have_sharing_friction": false,
                "bloks_app_url": null
              },
              "media_overlay_info": null,
              "media_preview": "ACof2ivoajKetP8AMHelyppkEOMVIppTigDn0NAEgNLUXTvRuoA54XMmOc5/zzQLh/X9RUSXOeCMVIWRuvP4VhzyW6NuVPYk+1uOScfWni7Y/wAQqDYn/wCrNO8paPaeQuTzLIun9jS/an9KoNGq9B+WRUXmD3/OqU77Ink8z//Z",
              "owner": {
                "id": "11319289292",
                "username": "clickimaginehr"
              },
              "is_video": false,
              "has_upcoming_event": false,
              "accessibility_caption": "Photo by Click Imagine in Jogbani. May be an image of flower, cloud and nature.",
              "edge_media_to_caption": {
                "edges": [
                  {
                    "node": {
                      "text": "Meet me where the sky touches the sea. . .\n\nP.C : @hidaytrahman\n.\nShot on the phone (Realme 5 pro)\n@realmeindia\n@realme5pro \n@real_me5pro \n@sun_set_hunter .\n.\n.\n.\n.\n.\n.\n.\n.\n#camismyeye #clickwithhidy #sunset #sunsets #sky #nature #sun #photography #landscape #clouds #travel #pics #sea #hikingculture #photooftheday #sunrise #naturephotography #skyporn #sunsetlovers #love #beautiful #instagood #realme5pro #naturelovers #picoftheday #landscapephotography #heavenonearth #captures #photographer #beautifulevening"
                    }
                  }
                ]
              },
              "edge_media_to_comment": {
                "count": 0
              },
              "comments_disabled": false,
              "taken_at_timestamp": 1634483611,
              "edge_liked_by": {
                "count": 10
              },
              "edge_media_preview_like": {
                "count": 10
              },
              "location": {
                "id": "1018850407",
                "has_public_page": true,
                "name": "Jogbani",
                "slug": "jogbani"
              },
              "thumbnail_src": "https://instagram.fdel52-1.fna.fbcdn.net/v/t51.2885-15/sh0.08/e35/c180.0.1080.1080a/s640x640/246397481_263940265648019_5831476138451305625_n.jpg?_nc_ht=instagram.fdel52-1.fna.fbcdn.net&_nc_cat=111&_nc_ohc=uXrt5kuGznEAX9OfKoJ&edm=ABfd0MgBAAAA&ccb=7-4&oh=00_AT9u_nruC2iKIHB42CiAUWSPpxvjeo2GgaXYLOsW7Oosqg&oe=6206535C&_nc_sid=7bff83",
              "thumbnail_resources": [
                {
                  "src": "https://instagram.fdel52-1.fna.fbcdn.net/v/t51.2885-15/e35/c180.0.1080.1080a/s150x150/246397481_263940265648019_5831476138451305625_n.jpg?_nc_ht=instagram.fdel52-1.fna.fbcdn.net&_nc_cat=111&_nc_ohc=uXrt5kuGznEAX9OfKoJ&edm=ABfd0MgBAAAA&ccb=7-4&oh=00_AT_egDh41S9exZHadpEsvI2ndxynWl7hYrVowowukkjwfA&oe=6205C3EC&_nc_sid=7bff83",
                  "config_width": 150,
                  "config_height": 150
                },
                {
                  "src": "https://instagram.fdel52-1.fna.fbcdn.net/v/t51.2885-15/e35/c180.0.1080.1080a/s240x240/246397481_263940265648019_5831476138451305625_n.jpg?_nc_ht=instagram.fdel52-1.fna.fbcdn.net&_nc_cat=111&_nc_ohc=uXrt5kuGznEAX9OfKoJ&edm=ABfd0MgBAAAA&ccb=7-4&oh=00_AT_O6yLSE_QqShKZHlvUMGhglVlD8LOt_--vdObQjV9u9Q&oe=6206CB6E&_nc_sid=7bff83",
                  "config_width": 240,
                  "config_height": 240
                },
                {
                  "src": "https://instagram.fdel52-1.fna.fbcdn.net/v/t51.2885-15/e35/c180.0.1080.1080a/s320x320/246397481_263940265648019_5831476138451305625_n.jpg?_nc_ht=instagram.fdel52-1.fna.fbcdn.net&_nc_cat=111&_nc_ohc=uXrt5kuGznEAX9OfKoJ&edm=ABfd0MgBAAAA&ccb=7-4&oh=00_AT9ibw2Se2IqZzlraD53vtI9v4skjln00ofAe0Z9ZCOQfA&oe=6205E554&_nc_sid=7bff83",
                  "config_width": 320,
                  "config_height": 320
                },
                {
                  "src": "https://instagram.fdel52-1.fna.fbcdn.net/v/t51.2885-15/e35/c180.0.1080.1080a/s480x480/246397481_263940265648019_5831476138451305625_n.jpg?_nc_ht=instagram.fdel52-1.fna.fbcdn.net&_nc_cat=111&_nc_ohc=uXrt5kuGznEAX9OfKoJ&edm=ABfd0MgBAAAA&ccb=7-4&oh=00_AT-mZhU3y4vBo3H4DI9xf9RH37MIygdv_-0soekT___KKA&oe=6206BA15&_nc_sid=7bff83",
                  "config_width": 480,
                  "config_height": 480
                },
                {
                  "src": "https://instagram.fdel52-1.fna.fbcdn.net/v/t51.2885-15/sh0.08/e35/c180.0.1080.1080a/s640x640/246397481_263940265648019_5831476138451305625_n.jpg?_nc_ht=instagram.fdel52-1.fna.fbcdn.net&_nc_cat=111&_nc_ohc=uXrt5kuGznEAX9OfKoJ&edm=ABfd0MgBAAAA&ccb=7-4&oh=00_AT9u_nruC2iKIHB42CiAUWSPpxvjeo2GgaXYLOsW7Oosqg&oe=6206535C&_nc_sid=7bff83",
                  "config_width": 640,
                  "config_height": 640
                }
              ],
              "coauthor_producers": []
            }
          },
          {
            "node": {
              "__typename": "GraphImage",
              "id": "2672805339633650091",
              "shortcode": "CUXtkuWoYmr",
              "dimensions": {
                "height": 1227,
                "width": 1080
              },
              "display_url": "https://instagram.fdel52-1.fna.fbcdn.net/v/t51.2885-15/e35/p1080x1080/243450743_555794362368400_5588347026750720301_n.jpg?_nc_ht=instagram.fdel52-1.fna.fbcdn.net&_nc_cat=104&_nc_ohc=ummqPFT9FBAAX9_ECPP&edm=ABfd0MgBAAAA&ccb=7-4&oh=00_AT-zWN04bauiuJq4cBREp11V9UBJstg1RVpoqxAsT6OO7g&oe=62076959&_nc_sid=7bff83",
              "edge_media_to_tagged_user": {
                "edges": []
              },
              "fact_check_overall_rating": null,
              "fact_check_information": null,
              "gating_info": null,
              "sharing_friction_info": {
                "should_have_sharing_friction": false,
                "bloks_app_url": null
              },
              "media_overlay_info": null,
              "media_preview": "ACUq5ul60qjNaEVmSMtx7Dr+dCTew21FXk7GfsOM0mK2GsgR8oKkD/OaozQGM4YfQgdabi47ijKM9t+zKlFKRRUlFi0wZF3dNw/rW+744QZPqen/ANesnT13MTx8o7+p4rTiQvnJGPf/AA7/AKVPPZ8onHmsOWRx1wfXioL8q0WcYIIxnt/n1qRozGCQAew5/wD1VGy7kywPORgZ/DP+FHtN1cOWzMF+pooZt3WiqGWLcna2PVO2f4v8/WtuO3kP8R+u3p+JauaBIpd7ep/Optd3EdE0MoGMn8VA/XNR3TPHGBuP3lGML659c1gbie9L2/Op5PP8EO4lFFFaiP/Z",
              "owner": {
                "id": "11319289292",
                "username": "clickimaginehr"
              },
              "is_video": false,
              "has_upcoming_event": false,
              "accessibility_caption": "Photo by Click Imagine in Jaipur Amber Fort India. May be an image of outdoors.",
              "edge_media_to_caption": {
                "edges": [
                  {
                    "node": {
                      "text": "Amber fort - gate\n.\n.\n.\n#clickwithhidy #camismyeye #historic #photography #india #jaipurdiaries #naturephotography #landscape"
                    }
                  }
                ]
              },
              "edge_media_to_comment": {
                "count": 0
              },
              "comments_disabled": false,
              "taken_at_timestamp": 1632843247,
              "edge_liked_by": {
                "count": 9
              },
              "edge_media_preview_like": {
                "count": 9
              },
              "location": {
                "id": "331377398",
                "has_public_page": true,
                "name": "Jaipur Amber Fort India",
                "slug": "jaipur-amber-fort-india"
              },
              "thumbnail_src": "https://instagram.fdel52-1.fna.fbcdn.net/v/t51.2885-15/sh0.08/e35/c0.98.1440.1440a/s640x640/243450743_555794362368400_5588347026750720301_n.jpg?_nc_ht=instagram.fdel52-1.fna.fbcdn.net&_nc_cat=104&_nc_ohc=ummqPFT9FBAAX9_ECPP&edm=ABfd0MgBAAAA&ccb=7-4&oh=00_AT_AujEUQ6tIanbZyuC82T6VInQ8Gce2UugQ-rqXdOuu8Q&oe=62068F34&_nc_sid=7bff83",
              "thumbnail_resources": [
                {
                  "src": "https://instagram.fdel52-1.fna.fbcdn.net/v/t51.2885-15/e35/c0.98.1440.1440a/s150x150/243450743_555794362368400_5588347026750720301_n.jpg?_nc_ht=instagram.fdel52-1.fna.fbcdn.net&_nc_cat=104&_nc_ohc=ummqPFT9FBAAX9_ECPP&edm=ABfd0MgBAAAA&ccb=7-4&oh=00_AT84XAm7c1LdB3wBwcksmhERn_ZPTgnkxhJoGCxtoMXC1g&oe=6205D125&_nc_sid=7bff83",
                  "config_width": 150,
                  "config_height": 150
                },
                {
                  "src": "https://instagram.fdel52-1.fna.fbcdn.net/v/t51.2885-15/e35/c0.98.1440.1440a/s240x240/243450743_555794362368400_5588347026750720301_n.jpg?_nc_ht=instagram.fdel52-1.fna.fbcdn.net&_nc_cat=104&_nc_ohc=ummqPFT9FBAAX9_ECPP&edm=ABfd0MgBAAAA&ccb=7-4&oh=00_AT9V7B7OKhQaHb_QqUUM1bnpOAEqrDFh3CvC2FRebOd1qg&oe=6205BB23&_nc_sid=7bff83",
                  "config_width": 240,
                  "config_height": 240
                },
                {
                  "src": "https://instagram.fdel52-1.fna.fbcdn.net/v/t51.2885-15/e35/c0.98.1440.1440a/s320x320/243450743_555794362368400_5588347026750720301_n.jpg?_nc_ht=instagram.fdel52-1.fna.fbcdn.net&_nc_cat=104&_nc_ohc=ummqPFT9FBAAX9_ECPP&edm=ABfd0MgBAAAA&ccb=7-4&oh=00_AT8Fg8KpwIBEDr2xhhrcaoolA_RmvIOcp5AUio3lai5_Fg&oe=62072B5D&_nc_sid=7bff83",
                  "config_width": 320,
                  "config_height": 320
                },
                {
                  "src": "https://instagram.fdel52-1.fna.fbcdn.net/v/t51.2885-15/e35/c0.98.1440.1440a/s480x480/243450743_555794362368400_5588347026750720301_n.jpg?_nc_ht=instagram.fdel52-1.fna.fbcdn.net&_nc_cat=104&_nc_ohc=ummqPFT9FBAAX9_ECPP&edm=ABfd0MgBAAAA&ccb=7-4&oh=00_AT-0iW4wI21TOEGkDW6uwci_7e9Pid3WU_cd3Nr6jusuug&oe=6205CBDC&_nc_sid=7bff83",
                  "config_width": 480,
                  "config_height": 480
                },
                {
                  "src": "https://instagram.fdel52-1.fna.fbcdn.net/v/t51.2885-15/sh0.08/e35/c0.98.1440.1440a/s640x640/243450743_555794362368400_5588347026750720301_n.jpg?_nc_ht=instagram.fdel52-1.fna.fbcdn.net&_nc_cat=104&_nc_ohc=ummqPFT9FBAAX9_ECPP&edm=ABfd0MgBAAAA&ccb=7-4&oh=00_AT_AujEUQ6tIanbZyuC82T6VInQ8Gce2UugQ-rqXdOuu8Q&oe=62068F34&_nc_sid=7bff83",
                  "config_width": 640,
                  "config_height": 640
                }
              ],
              "coauthor_producers": []
            }
          },
          {
            "node": {
              "__typename": "GraphImage",
              "id": "2656040892051630714",
              "shortcode": "CTcJx53pip6",
              "dimensions": {
                "height": 1080,
                "width": 1080
              },
              "display_url": "https://instagram.fdel52-1.fna.fbcdn.net/v/t51.2885-15/e35/s1080x1080/241177311_175630311347063_5744073141229953446_n.jpg?_nc_ht=instagram.fdel52-1.fna.fbcdn.net&_nc_cat=111&_nc_ohc=HqqenbepOsIAX_RFhvH&edm=ABfd0MgBAAAA&ccb=7-4&oh=00_AT-2-yLjxNPQ5TN9pZOMcqyWuwTbecZpGfO0MPgLssnT2w&oe=62072EA0&_nc_sid=7bff83",
              "edge_media_to_tagged_user": {
                "edges": [
                  {
                    "node": {
                      "user": {
                        "full_name": "SIGNI by SKYVIK",
                        "followed_by_viewer": false,
                        "id": "4247301359",
                        "is_verified": false,
                        "profile_pic_url": "https://instagram.fdel52-1.fna.fbcdn.net/v/t51.2885-19/s150x150/134816384_209267880860128_9127758047696044928_n.jpg?_nc_ht=instagram.fdel52-1.fna.fbcdn.net&_nc_cat=104&_nc_ohc=a5RT950bQSsAX9TLKF7&edm=ABfd0MgBAAAA&ccb=7-4&oh=00_AT_p9f5fLlvy8UQo-rNP65bzh6Cqm9uiQC1Pb04LOPB0bA&oe=62063091&_nc_sid=7bff83",
                        "username": "skyviksigni"
                      },
                      "x": 0.5,
                      "y": 0.5
                    }
                  },
                  {
                    "node": {
                      "user": {
                        "full_name": "Hidayt Rahman",
                        "followed_by_viewer": false,
                        "id": "3280824343",
                        "is_verified": false,
                        "profile_pic_url": "https://instagram.fdel52-1.fna.fbcdn.net/v/t51.2885-19/s150x150/271896126_650254582841380_43292338451860659_n.jpg?_nc_ht=instagram.fdel52-1.fna.fbcdn.net&_nc_cat=104&_nc_ohc=TEXlledQFZsAX96KEdD&edm=ABfd0MgBAAAA&ccb=7-4&oh=00_AT_Nff30aHli9zOTqmGyXNBkhj0qkJjqHSUMrbKqZl7IMA&oe=62076EE4&_nc_sid=7bff83",
                        "username": "hidaytrahman"
                      },
                      "x": 0.075555542,
                      "y": 0.6524444173
                    }
                  }
                ]
              },
              "fact_check_overall_rating": null,
              "fact_check_information": null,
              "gating_info": null,
              "sharing_friction_info": {
                "should_have_sharing_friction": false,
                "bloks_app_url": null
              },
              "media_overlay_info": null,
              "media_preview": "ACoq57bitCx+/tqNYixzWjZwqGOO1c1SS5WZNlq4UFeaguYlMfAp98+xaWKZZI81yK6Sku5l5mI6FRUfmv6mtIyLnB6Cqx8uutS7o1TNJI1Y4qzDFsJI70sarjNSoRXDKT2MrmfeIZSB2ziqKwsjbeg/StmRgOTVKSdSfetoSdrW0KT6FeVMDigWoIzWkgDLuNUGuACapSb0XQLt7EdtOwTnmnw3mzIY5qqPuVVateRSvcu17lx7vcx96dGwkIFZgq7afeqpRUVoDVjWlfam0d6zvsxqWU/NUw6VgvdWnUhaH//Z",
              "owner": {
                "id": "11319289292",
                "username": "clickimaginehr"
              },
              "is_video": false,
              "has_upcoming_event": false,
              "accessibility_caption": "Photo by Click Imagine in India with @hidaytrahman, and @skyviksigni. May be a closeup of nature.",
              "edge_media_to_caption": {
                "edges": [
                  {
                    "node": {
                      "text": "Beautiful spider but tiny .\n.\nPhone : @iphone (iPhone 11 Pro)\nMacro lense : @skyviksigni SIGNi pro 2 in one\n\nUse my hashtag - #clickwithhidy and #camismyeye \n#macrophotography #macro #nature #naturephotography #photography #bugs #photooftheday #macros #naturelovers #instagood #flowerstagram #insect #insects #photographer #closeup #art #macro_captures #mobilephotography #wildlife #skyviksigni #beautiful #picoftheday #spider #wildlifephotography #macro_perfection #plants #beautifulspider"
                    }
                  }
                ]
              },
              "edge_media_to_comment": {
                "count": 0
              },
              "comments_disabled": false,
              "taken_at_timestamp": 1630844769,
              "edge_liked_by": {
                "count": 11
              },
              "edge_media_preview_like": {
                "count": 11
              },
              "location": {
                "id": "109524955741121",
                "has_public_page": true,
                "name": "India",
                "slug": "india"
              },
              "thumbnail_src": "https://instagram.fdel52-1.fna.fbcdn.net/v/t51.2885-15/sh0.08/e35/s640x640/241177311_175630311347063_5744073141229953446_n.jpg?_nc_ht=instagram.fdel52-1.fna.fbcdn.net&_nc_cat=111&_nc_ohc=HqqenbepOsIAX_RFhvH&edm=ABfd0MgBAAAA&ccb=7-4&oh=00_AT_6BVxLLv6B8TtQFj3L1doh7K85cQTH1fzCi_Rm1IYAfw&oe=6205E7DC&_nc_sid=7bff83",
              "thumbnail_resources": [
                {
                  "src": "https://instagram.fdel52-1.fna.fbcdn.net/v/t51.2885-15/e35/s150x150/241177311_175630311347063_5744073141229953446_n.jpg?_nc_ht=instagram.fdel52-1.fna.fbcdn.net&_nc_cat=111&_nc_ohc=HqqenbepOsIAX_RFhvH&edm=ABfd0MgBAAAA&ccb=7-4&oh=00_AT95uhLN78eQvfaUNwNViP9dAvNGyT5WXGq6uPrm2DP8-A&oe=62069A5F&_nc_sid=7bff83",
                  "config_width": 150,
                  "config_height": 150
                },
                {
                  "src": "https://instagram.fdel52-1.fna.fbcdn.net/v/t51.2885-15/e35/s240x240/241177311_175630311347063_5744073141229953446_n.jpg?_nc_ht=instagram.fdel52-1.fna.fbcdn.net&_nc_cat=111&_nc_ohc=HqqenbepOsIAX_RFhvH&edm=ABfd0MgBAAAA&ccb=7-4&oh=00_AT9R7FEqB07nRlevbBUJBtSS9_hHCqgf-I1Ps2hE58S4sw&oe=62069159&_nc_sid=7bff83",
                  "config_width": 240,
                  "config_height": 240
                },
                {
                  "src": "https://instagram.fdel52-1.fna.fbcdn.net/v/t51.2885-15/e35/s320x320/241177311_175630311347063_5744073141229953446_n.jpg?_nc_ht=instagram.fdel52-1.fna.fbcdn.net&_nc_cat=111&_nc_ohc=HqqenbepOsIAX_RFhvH&edm=ABfd0MgBAAAA&ccb=7-4&oh=00_AT9qG7dsln-AGd6F24KOgHE7p8ztgAWWFBV7UInfu5bmNQ&oe=6206FAA7&_nc_sid=7bff83",
                  "config_width": 320,
                  "config_height": 320
                },
                {
                  "src": "https://instagram.fdel52-1.fna.fbcdn.net/v/t51.2885-15/e35/s480x480/241177311_175630311347063_5744073141229953446_n.jpg?_nc_ht=instagram.fdel52-1.fna.fbcdn.net&_nc_cat=111&_nc_ohc=HqqenbepOsIAX_RFhvH&edm=ABfd0MgBAAAA&ccb=7-4&oh=00_AT_Qs0Zo3kn3uxON1OBwl_uIvdyatmwBxvtuebSfQ7jZUg&oe=62067122&_nc_sid=7bff83",
                  "config_width": 480,
                  "config_height": 480
                },
                {
                  "src": "https://instagram.fdel52-1.fna.fbcdn.net/v/t51.2885-15/sh0.08/e35/s640x640/241177311_175630311347063_5744073141229953446_n.jpg?_nc_ht=instagram.fdel52-1.fna.fbcdn.net&_nc_cat=111&_nc_ohc=HqqenbepOsIAX_RFhvH&edm=ABfd0MgBAAAA&ccb=7-4&oh=00_AT_6BVxLLv6B8TtQFj3L1doh7K85cQTH1fzCi_Rm1IYAfw&oe=6205E7DC&_nc_sid=7bff83",
                  "config_width": 640,
                  "config_height": 640
                }
              ],
              "coauthor_producers": []
            }
          },
          {
            "node": {
              "__typename": "GraphImage",
              "id": "2647468551499447960",
              "shortcode": "CS9sp7mJH6Y",
              "dimensions": {
                "height": 1350,
                "width": 1080
              },
              "display_url": "https://instagram.fdel52-1.fna.fbcdn.net/v/t51.2885-15/e35/p1080x1080/240410099_607253000659813_7575046011210745347_n.jpg?_nc_ht=instagram.fdel52-1.fna.fbcdn.net&_nc_cat=101&_nc_ohc=21sT8ypAhYwAX9UO4ZM&edm=ABfd0MgBAAAA&ccb=7-4&oh=00_AT-6Zld0hqpxeNm9UU6Y_nyoiqh50E5y76JbWe6KjBTviw&oe=62065EB6&_nc_sid=7bff83",
              "edge_media_to_tagged_user": {
                "edges": [
                  {
                    "node": {
                      "user": {
                        "full_name": "The Local Train",
                        "followed_by_viewer": false,
                        "id": "306048276",
                        "is_verified": true,
                        "profile_pic_url": "https://instagram.fdel52-1.fna.fbcdn.net/v/t51.2885-19/s150x150/96808532_240405703944168_3234802881529905152_n.jpg?_nc_ht=instagram.fdel52-1.fna.fbcdn.net&_nc_cat=100&_nc_ohc=Dvu6M0ONvv8AX_qpHv3&edm=ABfd0MgBAAAA&ccb=7-4&oh=00_AT8D5I8dyrA797zgI8CmQnfcjaNxPsI7-zWUrTDgq5305Q&oe=6206CB35&_nc_sid=7bff83",
                        "username": "thelocaltrain"
                      },
                      "x": 0.855111084,
                      "y": 0.8142222087
                    }
                  },
                  {
                    "node": {
                      "user": {
                        "full_name": "Roadtrip | Travel Diary",
                        "followed_by_viewer": false,
                        "id": "37042844169",
                        "is_verified": false,
                        "profile_pic_url": "https://instagram.fdel52-1.fna.fbcdn.net/v/t51.2885-19/s150x150/214392296_410851900254148_5659620855549796713_n.jpg?_nc_ht=instagram.fdel52-1.fna.fbcdn.net&_nc_cat=104&_nc_ohc=E9CJ8gBmlusAX_4jeDt&edm=ABfd0MgBAAAA&ccb=7-4&oh=00_AT8wewg3TVL88DRYQtZMQKbaLYhPK3cI72mSomLWDKyJIg&oe=6206E630&_nc_sid=7bff83",
                        "username": "roadtrip.diary"
                      },
                      "x": 0.8826666667,
                      "y": 0.9836601298
                    }
                  },
                  {
                    "node": {
                      "user": {
                        "full_name": "Hidayt Rahman",
                        "followed_by_viewer": false,
                        "id": "3280824343",
                        "is_verified": false,
                        "profile_pic_url": "https://instagram.fdel52-1.fna.fbcdn.net/v/t51.2885-19/s150x150/271896126_650254582841380_43292338451860659_n.jpg?_nc_ht=instagram.fdel52-1.fna.fbcdn.net&_nc_cat=104&_nc_ohc=TEXlledQFZsAX96KEdD&edm=ABfd0MgBAAAA&ccb=7-4&oh=00_AT_Nff30aHli9zOTqmGyXNBkhj0qkJjqHSUMrbKqZl7IMA&oe=62076EE4&_nc_sid=7bff83",
                        "username": "hidaytrahman"
                      },
                      "x": 0.1804444173,
                      "y": 0.9537777507
                    }
                  }
                ]
              },
              "fact_check_overall_rating": null,
              "fact_check_information": null,
              "gating_info": null,
              "sharing_friction_info": {
                "should_have_sharing_friction": false,
                "bloks_app_url": null
              },
              "media_overlay_info": null,
              "media_preview": "ACEq1AT2GalX34pUlTgA5JGfw9aGdf4v1oAXaDVee5it85OWAyB6+gz/AJ4pk19FDwxyfRf8/wBc1kX88VwNy5DDgDHXPf8Al9KQEf8Aacvt/n8aKz/Jk/uH8jRSGXo3kQ5Vj0+lPlZ2ADuDnnls/p6+1ShwehH4ilJGOg/P/EVjzNb/ANfgaWGQRRvwWyBnqPQdP8DUsTKm7hRhvlOP4aRSp6ZH0K/4UrAe/wCQqubsKxL9qT1/nRVXA9T+X/16KfP/AF/TDlIQ4bsDj8P06/lRtOMcgnoOpJ+h6D+dVzyKfEx8lmyd3Az36jv1qlqIkRWDYUg4GWPQD8f06deBS+a55IOB1I5HP5UYxBxx8wH6Zpf+WA93OfyFMQnn+x/I0VFk0UDP/9k=",
              "owner": {
                "id": "11319289292",
                "username": "clickimaginehr"
              },
              "is_video": false,
              "has_upcoming_event": false,
              "accessibility_caption": "Photo by Click Imagine in India with @thelocaltrain, @hidaytrahman, and @roadtrip.diary. May be an image of nature and railroad.",
              "edge_media_to_caption": {
                "edges": [
                  {
                    "node": {
                      "text": "Unstoppable road trip\n.\n(shot on the iphone)\n.\nPC : @hidaytrahman . @iphone \n@the.inspired.traveller .\n.\n.\n.\n.\n\n#camismyeye #clickwithhidy #shotoniphone #nature #mountains #travel #uttarakhand #landscape #naturephotography #india #travelphotography #roadtrip #hiking #clouds #bihartourism #sky #sunset #adventure #landscapephotography #wanderlust #love #roadtrips #snow #photooftheday #instagood #roads #chopta #forest #travelgram #trees"
                    }
                  }
                ]
              },
              "edge_media_to_comment": {
                "count": 11
              },
              "comments_disabled": false,
              "taken_at_timestamp": 1629822866,
              "edge_liked_by": {
                "count": 19
              },
              "edge_media_preview_like": {
                "count": 19
              },
              "location": {
                "id": "109524955741121",
                "has_public_page": true,
                "name": "India",
                "slug": "india"
              },
              "thumbnail_src": "https://instagram.fdel52-1.fna.fbcdn.net/v/t51.2885-15/sh0.08/e35/c0.180.1440.1440a/s640x640/240410099_607253000659813_7575046011210745347_n.jpg?_nc_ht=instagram.fdel52-1.fna.fbcdn.net&_nc_cat=101&_nc_ohc=21sT8ypAhYwAX9UO4ZM&edm=ABfd0MgBAAAA&ccb=7-4&oh=00_AT-QZPASgG2GilPShu2yNzes26YiMnHJLUsy5evw5lprjw&oe=62061552&_nc_sid=7bff83",
              "thumbnail_resources": [
                {
                  "src": "https://instagram.fdel52-1.fna.fbcdn.net/v/t51.2885-15/e35/c0.180.1440.1440a/s150x150/240410099_607253000659813_7575046011210745347_n.jpg?_nc_ht=instagram.fdel52-1.fna.fbcdn.net&_nc_cat=101&_nc_ohc=21sT8ypAhYwAX9UO4ZM&edm=ABfd0MgBAAAA&ccb=7-4&oh=00_AT8StHrXmsgMA3wFkMsSlfFNn7acPs_y55AlAArstvW-2Q&oe=6206BEE2&_nc_sid=7bff83",
                  "config_width": 150,
                  "config_height": 150
                },
                {
                  "src": "https://instagram.fdel52-1.fna.fbcdn.net/v/t51.2885-15/e35/c0.180.1440.1440a/s240x240/240410099_607253000659813_7575046011210745347_n.jpg?_nc_ht=instagram.fdel52-1.fna.fbcdn.net&_nc_cat=101&_nc_ohc=21sT8ypAhYwAX9UO4ZM&edm=ABfd0MgBAAAA&ccb=7-4&oh=00_AT-eQP35_vbDucu35yeWfR1qtzU1u0ifpgPpOEeb1d__9g&oe=62061268&_nc_sid=7bff83",
                  "config_width": 240,
                  "config_height": 240
                },
                {
                  "src": "https://instagram.fdel52-1.fna.fbcdn.net/v/t51.2885-15/e35/c0.180.1440.1440a/s320x320/240410099_607253000659813_7575046011210745347_n.jpg?_nc_ht=instagram.fdel52-1.fna.fbcdn.net&_nc_cat=101&_nc_ohc=21sT8ypAhYwAX9UO4ZM&edm=ABfd0MgBAAAA&ccb=7-4&oh=00_AT-TJ-NN7vFnL1UHb_lMZWWdvg-fvBlINwHgV_nmlP9jjw&oe=6205F6DA&_nc_sid=7bff83",
                  "config_width": 320,
                  "config_height": 320
                },
                {
                  "src": "https://instagram.fdel52-1.fna.fbcdn.net/v/t51.2885-15/e35/c0.180.1440.1440a/s480x480/240410099_607253000659813_7575046011210745347_n.jpg?_nc_ht=instagram.fdel52-1.fna.fbcdn.net&_nc_cat=101&_nc_ohc=21sT8ypAhYwAX9UO4ZM&edm=ABfd0MgBAAAA&ccb=7-4&oh=00_AT_9O7-FzHdRfT56CLYSNQAsQKO614KxbP_Dnlm0Afropg&oe=6206CBDF&_nc_sid=7bff83",
                  "config_width": 480,
                  "config_height": 480
                },
                {
                  "src": "https://instagram.fdel52-1.fna.fbcdn.net/v/t51.2885-15/sh0.08/e35/c0.180.1440.1440a/s640x640/240410099_607253000659813_7575046011210745347_n.jpg?_nc_ht=instagram.fdel52-1.fna.fbcdn.net&_nc_cat=101&_nc_ohc=21sT8ypAhYwAX9UO4ZM&edm=ABfd0MgBAAAA&ccb=7-4&oh=00_AT-QZPASgG2GilPShu2yNzes26YiMnHJLUsy5evw5lprjw&oe=62061552&_nc_sid=7bff83",
                  "config_width": 640,
                  "config_height": 640
                }
              ],
              "coauthor_producers": []
            }
          }
        ]
      },
      "edge_saved_media": {
        "count": 0,
        "page_info": {
          "has_next_page": false,
          "end_cursor": null
        },
        "edges": []
      },
      "edge_media_collections": {
        "count": 0,
        "page_info": {
          "has_next_page": false,
          "end_cursor": null
        },
        "edges": []
      },
      "edge_related_profiles": {
        "edges": []
      }
    }
  },
  "toast_content_on_load": null,
  "show_view_shop": false,
  "profile_pic_edit_sync_props": {
    "show_change_profile_pic_confirm_dialog": false,
    "show_profile_pic_sync_reminders": false,
    "identity_id": "",
    "remove_profile_pic_header": null,
    "remove_profile_pic_subtext": null,
    "remove_profile_pic_confirm_cta": null,
    "remove_profile_pic_cancel_cta": null,
    "is_business_central_identity": false,
    "change_profile_pic_actions_screen_header": [
      "C",
      "h",
      "a",
      "n",
      "g",
      "e",
      " ",
      "P",
      "r",
      "o",
      "f",
      "i",
      "l",
      "e",
      " ",
      "P",
      "h",
      "o",
      "t",
      "o"
    ],
    "change_profile_pic_actions_screen_subheader": [
      "I",
      "n",
      "s",
      "t",
      "a",
      "g",
      "r",
      "a",
      "m",
      ",",
      " ",
      "F",
      "a",
      "c",
      "e",
      "b",
      "o",
      "o",
      "k"
    ],
    "change_profile_pic_actions_screen_upload_cta": [
      "U",
      "p",
      "l",
      "o",
      "a",
      "d",
      " ",
      "P",
      "h",
      "o",
      "t",
      "o"
    ],
    "change_profile_pic_actions_screen_remove_cta": [
      "R",
      "e",
      "m",
      "o",
      "v",
      "e",
      " ",
      "C",
      "u",
      "r",
      "r",
      "e",
      "n",
      "t",
      " ",
      "P",
      "h",
      "o",
      "t",
      "o"
    ],
    "change_profile_pic_actions_screen_cancel_cta": [
      "C",
      "a",
      "n",
      "c",
      "e",
      "l"
    ]
  },
  "always_show_message_button_to_pro_account": false
}
